.gitignore
.travis.yml
CHANGES.rst
LICENSE.txt
MANIFEST.in
README.rst
dev-reqs.txt
development.ini
message-extraction.ini
production.ini
requirements.txt
run
runapp.py
setup.cfg
setup.py
testreqs.txt
tests-require.txt
CheesePrism.egg-info/PKG-INFO
CheesePrism.egg-info/SOURCES.txt
CheesePrism.egg-info/dependency_links.txt
CheesePrism.egg-info/entry_points.txt
CheesePrism.egg-info/not-zip-safe
CheesePrism.egg-info/requires.txt
CheesePrism.egg-info/top_level.txt
cheeseprism/__init__.py
cheeseprism/auth.py
cheeseprism/desc.py
cheeseprism/event.py
cheeseprism/index.py
cheeseprism/pipext.py
cheeseprism/request.py
cheeseprism/resources.py
cheeseprism/rpc.py
cheeseprism/utils.py
cheeseprism/views.py
cheeseprism/wsgiapp.py
cheeseprism/locale/CheesePrism.pot
cheeseprism/locale/de/LC_MESSAGES/CheesePrism.mo
cheeseprism/locale/de/LC_MESSAGES/CheesePrism.po
cheeseprism/locale/fr/LC_MESSAGES/CheesePrism.mo
cheeseprism/locale/fr/LC_MESSAGES/CheesePrism.po
cheeseprism/static/favicon.ico
cheeseprism/static/footerbg.png
cheeseprism/static/headerbg.png
cheeseprism/static/ie6.css
cheeseprism/static/logo.png
cheeseprism/static/middlebg.png
cheeseprism/static/pylons.css
cheeseprism/static/pyramid-small.png
cheeseprism/static/pyramid.png
cheeseprism/static/style.css
cheeseprism/static/transparent.gif
cheeseprism/templates/base.html
cheeseprism/templates/filter.html
cheeseprism/templates/find_packages.html
cheeseprism/templates/index.html
cheeseprism/templates/instructions.html
cheeseprism/templates/layout.html
cheeseprism/templates/list.html
cheeseprism/templates/regenerate.html
cheeseprism/templates/requirements_upload.html
cheeseprism/templates/index/base.html
cheeseprism/templates/index/home.html
cheeseprism/templates/index/leaf.html
cheeseprism/txn/__init__.py
cheeseprism/txn/datamanager.py
cheeseprism/txn/savepoint.py
cheeseprism/txn/tests/test_jsondm.py
doc/DESIGN.rst
doc/TODO.rst
doc/nginx-example.conf
doc/example-index/dummypackage-0.0dev.tar.gz
doc/example-index/dummypackage/index.html
tests/index.json
tests/req-1.txt
tests/test_auth.py
tests/test_desc.py
tests/test_envloader.py
tests/test_index.py
tests/test_main.py
tests/test_pipext.py
tests/test_request.py
tests/test_rpc.py
tests/test_views.py
