Metadata-Version: 1.0
Name: CheesePrism
Version: 0.3
Summary: CheesePrism
Home-page: https://github.com/SurveyMonkey/CheesePrism
Author: Whit Morriss (et al.)
Author-email: whit-at-surveymonkey-dot-com
License: UNKNOWN
Keywords: web pyramid pylons
Platform: UNKNOWN
Classifier: Programming Language :: Python
Classifier: Framework :: Pylons
Classifier: Topic :: Internet :: WWW/HTTP
Classifier: Topic :: Internet :: WWW/HTTP :: WSGI :: Application
